{
    "openapi": "3.0.01",
    "info": {
      "title": "PUB API",
      "version": "1.0"
    },
    "paths": {
      "/nieuws": {
        "get": {
          "summary": "Your GET endpoint",
          "tags": [],
          "operationId": "get-nieuws",
          "responses": {
            "200": {
              "description": "OK",
              "content": {
                "application/json": {
                  "schema": {
                    "description": "",
                    "type": "object",
                    "properties": {
                      "Nieuws": {
                        "type": "array",
                        "uniqueItems": true,
                        "minItems": 1,
                        "items": {
                          "required": [
                            "id",
                            "title",
                            "content",
                            "excerpt",
                            "date",
                            "slug",
                            "post_status",
                            "highlighted",
                            "notes",
                            "synonyms"
                          ],
                          "properties": {
                            "id": {
                              "type": "number"
                            },
                            "title": {
                              "type": "string",
                              "minLength": 1
                            },
                            "content": {
                              "type": "string",
                              "minLength": 1
                            },
                            "excerpt": {
                              "type": "string"
                            },
                            "date": {
                              "type": "string",
                              "minLength": 1
                            },
                            "slug": {
                              "type": "string",
                              "minLength": 1
                            },
                            "post_status": {
                              "type": "string",
                              "minLength": 1
                            },
                            "connected": {
                              "type": "object",
                              "properties": {
                                "openpub-item_to_openpub-theme": {
                                  "type": "array",
                                  "items": {
                                    "required": [],
                                    "properties": {}
                                  }
                                },
                                "openpub-item_to_openpub-subtheme": {
                                  "type": "array",
                                  "items": {
                                    "required": [],
                                    "properties": {}
                                  }
                                },
                                "openpub-item_to_openpub-location": {
                                  "type": "array",
                                  "items": {
                                    "required": [],
                                    "properties": {}
                                  }
                                },
                                "openpub-item_to_openpub-item": {
                                  "type": "array",
                                  "items": {
                                    "required": [],
                                    "properties": {}
                                  }
                                }
                              },
                              "required": [
                                "openpub-item_to_openpub-theme",
                                "openpub-item_to_openpub-subtheme",
                                "openpub-item_to_openpub-location",
                                "openpub-item_to_openpub-item"
                              ]
                            },
                            "downloads": {
                              "type": "array",
                              "items": {
                                "required": [],
                                "properties": {}
                              }
                            },
                            "expired": {
                              "type": "object",
                              "properties": {
                                "message": {
                                  "type": "string"
                                },
                                "status": {
                                  "type": "boolean"
                                },
                                "on": {
                                  "type": "object",
                                  "properties": {
                                    "date": {
                                      "type": "string",
                                      "minLength": 1
                                    },
                                    "timezone_type": {
                                      "type": "number"
                                    },
                                    "timezone": {
                                      "type": "string",
                                      "minLength": 1
                                    }
                                  },
                                  "required": [
                                    "date",
                                    "timezone_type",
                                    "timezone"
                                  ]
                                }
                              },
                              "required": [
                                "message",
                                "status",
                                "on"
                              ]
                            },
                            "highlighted": {
                              "type": "boolean"
                            },
                            "image": {
                              "type": "object",
                              "properties": {
                                "title": {
                                  "type": "string",
                                  "minLength": 1
                                },
                                "description": {
                                  "type": "string"
                                },
                                "caption": {
                                  "type": "string"
                                },
                                "alt": {
                                  "type": "string"
                                },
                                "rendered": {
                                  "type": "string",
                                  "minLength": 1
                                },
                                "sizes": {
                                  "type": "string",
                                  "minLength": 1
                                },
                                "srcset": {
                                  "type": "string",
                                  "minLength": 1
                                },
                                "meta": {
                                  "type": "object",
                                  "properties": {
                                    "width": {
                                      "type": "number"
                                    },
                                    "height": {
                                      "type": "number"
                                    },
                                    "file": {
                                      "type": "string",
                                      "minLength": 1
                                    },
                                    "sizes": {
                                      "type": "object",
                                      "properties": {
                                        "medium": {
                                          "type": "object",
                                          "properties": {
                                            "file": {
                                              "type": "string",
                                              "minLength": 1
                                            },
                                            "width": {
                                              "type": "number"
                                            },
                                            "height": {
                                              "type": "number"
                                            },
                                            "mime-type": {
                                              "type": "string",
                                              "minLength": 1
                                            },
                                            "url": {
                                              "type": "string",
                                              "minLength": 1
                                            },
                                            "rendered": {
                                              "type": "string",
                                              "minLength": 1
                                            }
                                          },
                                          "required": [
                                            "file",
                                            "width",
                                            "height",
                                            "mime-type",
                                            "url",
                                            "rendered"
                                          ]
                                        },
                                        "large": {
                                          "type": "object",
                                          "properties": {
                                            "file": {
                                              "type": "string",
                                              "minLength": 1
                                            },
                                            "width": {
                                              "type": "number"
                                            },
                                            "height": {
                                              "type": "number"
                                            },
                                            "mime-type": {
                                              "type": "string",
                                              "minLength": 1
                                            },
                                            "url": {
                                              "type": "string",
                                              "minLength": 1
                                            },
                                            "rendered": {
                                              "type": "string",
                                              "minLength": 1
                                            }
                                          },
                                          "required": [
                                            "file",
                                            "width",
                                            "height",
                                            "mime-type",
                                            "url",
                                            "rendered"
                                          ]
                                        },
                                        "thumbnail": {
                                          "type": "object",
                                          "properties": {
                                            "file": {
                                              "type": "string",
                                              "minLength": 1
                                            },
                                            "width": {
                                              "type": "number"
                                            },
                                            "height": {
                                              "type": "number"
                                            },
                                            "mime-type": {
                                              "type": "string",
                                              "minLength": 1
                                            },
                                            "url": {
                                              "type": "string",
                                              "minLength": 1
                                            },
                                            "rendered": {
                                              "type": "string",
                                              "minLength": 1
                                            }
                                          },
                                          "required": [
                                            "file",
                                            "width",
                                            "height",
                                            "mime-type",
                                            "url",
                                            "rendered"
                                          ]
                                        },
                                        "medium_large": {
                                          "type": "object",
                                          "properties": {
                                            "file": {
                                              "type": "string",
                                              "minLength": 1
                                            },
                                            "width": {
                                              "type": "number"
                                            },
                                            "height": {
                                              "type": "number"
                                            },
                                            "mime-type": {
                                              "type": "string",
                                              "minLength": 1
                                            },
                                            "url": {
                                              "type": "string",
                                              "minLength": 1
                                            },
                                            "rendered": {
                                              "type": "string",
                                              "minLength": 1
                                            }
                                          },
                                          "required": [
                                            "file",
                                            "width",
                                            "height",
                                            "mime-type",
                                            "url",
                                            "rendered"
                                          ]
                                        },
                                        "full": {
                                          "type": "object",
                                          "properties": {
                                            "file": {
                                              "type": "string",
                                              "minLength": 1
                                            },
                                            "width": {
                                              "type": "number"
                                            },
                                            "height": {
                                              "type": "number"
                                            },
                                            "mime-type": {
                                              "type": "string",
                                              "minLength": 1
                                            },
                                            "url": {
                                              "type": "string",
                                              "minLength": 1
                                            },
                                            "rendered": {
                                              "type": "string",
                                              "minLength": 1
                                            }
                                          },
                                          "required": [
                                            "file",
                                            "width",
                                            "height",
                                            "mime-type",
                                            "url",
                                            "rendered"
                                          ]
                                        }
                                      },
                                      "required": [
                                        "medium",
                                        "large",
                                        "thumbnail",
                                        "medium_large",
                                        "full"
                                      ]
                                    }
                                  },
                                  "required": [
                                    "width",
                                    "height",
                                    "file",
                                    "sizes"
                                  ]
                                }
                              },
                              "required": [
                                "title",
                                "description",
                                "caption",
                                "alt",
                                "rendered",
                                "sizes",
                                "srcset",
                                "meta"
                              ]
                            },
                            "links": {
                              "type": "array",
                              "items": {
                                "required": [],
                                "properties": {}
                              }
                            },
                            "notes": {
                              "type": "string"
                            },
                            "synonyms": {
                              "type": "string"
                            },
                            "taxonomies": {
                              "type": "object",
                              "properties": {
                                "openpub-audience": {
                                  "type": "array",
                                  "uniqueItems": true,
                                  "minItems": 1,
                                  "items": {
                                    "required": [
                                      "id",
                                      "name",
                                      "slug"
                                    ],
                                    "properties": {
                                      "id": {
                                        "type": "number"
                                      },
                                      "name": {
                                        "type": "string",
                                        "minLength": 1
                                      },
                                      "slug": {
                                        "type": "string",
                                        "minLength": 1
                                      }
                                    }
                                  }
                                },
                                "openpub-type": {
                                  "type": "array",
                                  "uniqueItems": true,
                                  "minItems": 1,
                                  "items": {
                                    "required": [
                                      "id",
                                      "name",
                                      "slug"
                                    ],
                                    "properties": {
                                      "id": {
                                        "type": "number"
                                      },
                                      "name": {
                                        "type": "string",
                                        "minLength": 1
                                      },
                                      "slug": {
                                        "type": "string",
                                        "minLength": 1
                                      }
                                    }
                                  }
                                },
                                "openpub-usage": {
                                  "type": "array",
                                  "uniqueItems": true,
                                  "minItems": 1,
                                  "items": {
                                    "required": [
                                      "id",
                                      "name",
                                      "slug"
                                    ],
                                    "properties": {
                                      "id": {
                                        "type": "number"
                                      },
                                      "name": {
                                        "type": "string",
                                        "minLength": 1
                                      },
                                      "slug": {
                                        "type": "string",
                                        "minLength": 1
                                      }
                                    }
                                  }
                                },
                                "openpub-show-on": {
                                  "type": "array",
                                  "items": {
                                    "required": [],
                                    "properties": {}
                                  }
                                }
                              },
                              "required": [
                                "openpub-audience",
                                "openpub-type",
                                "openpub-usage",
                                "openpub-show-on"
                              ]
                            }
                          }
                        }
                      }
                    },
                    "required": [
                      "Nieuws"
                    ],
                    "x-examples": {
                      "example-1": {
                        "Nieuws": [
                          {
                            "id": 7367,
                            "title": "Voorbelasten bouwlocatie de Teisterbant",
                            "content": "<p>In de loop van 2022 start de bouw van 55 woningen in Kerk-Avezaath. Dit gebeurt aan de noordkant van het dorp.</p>\n<p>Voordat er kan worden gebouwd, moet de grond eerst worden voorbelast. Voorbelast betekent dat de grond bouwrijp gemaakt wordt. Door het voorbelasten wordt de grond verdicht en wordt de zetting (verzakking) van de grond versneld. Hiervoor wordt op de bouwlocatie een pakket van ongeveer één meter schoon zand aangebracht. Dit zand blijft een half jaar liggen.</p>\n<p>De vrachtwagens rijden de volgende routes:</p>\n<ul>\n<li>Via de Woerd, Dorpsstraat en Achterstraat wordt het zand aangevoerd door de vrachtwagens.</li>\n<li>De vrachtwagens rijden via de Achterstraat, Dorpsstraat, Noordereind en Burensedijk weer terug.</li>\n</ul>\n<p>Bij de keuze van de routes hebben we zoveel mogelijk rekening gehouden met de verkeersveiligheid en verkeersoverlast. De aanvoer van het zand start op 13 april 2022 en duurt ongeveer drie weken.</p>\n<p>Deze werkzaamheden zijn dus niet de bouwwerkzaamheden, maar de voorbereiding daarop.<br />\nOver de bouwwerkzaamheden informeren we u later. Heeft u vragen? Neem contact op met de heer R. Melis via het telefoonnummer 06 54 38 22 36.</p>\n",
                            "excerpt": "",
                            "date": "2022-04-12 11:22:03",
                            "slug": "voorbelasten-bouwlocatie-de-teisterbant",
                            "post_status": "publish",
                            "connected": {
                              "openpub-item_to_openpub-theme": [],
                              "openpub-item_to_openpub-subtheme": [],
                              "openpub-item_to_openpub-location": [],
                              "openpub-item_to_openpub-item": []
                            },
                            "downloads": [],
                            "expired": {
                              "message": "",
                              "status": false,
                              "on": {
                                "date": "2022-05-15 00:00:00.000000",
                                "timezone_type": 3,
                                "timezone": "Europe/Amsterdam"
                              }
                            },
                            "highlighted": false,
                            "image": {
                              "title": "bandensporen",
                              "description": "",
                              "caption": "",
                              "alt": "",
                              "rendered": "<img width=\"1024\" height=\"576\" src=\"https://openpub.buren.nl/wp-content/uploads/2022/04/bandensporen-e1649755297420-1024x576.jpg\" class=\"attachment-large size-large\" alt=\"\" loading=\"lazy\" srcset=\"https://openpub.buren.nl/wp-content/uploads/2022/04/bandensporen-e1649755297420-1024x576.jpg 1024w, https://openpub.buren.nl/wp-content/uploads/2022/04/bandensporen-e1649755297420-300x169.jpg 300w, https://openpub.buren.nl/wp-content/uploads/2022/04/bandensporen-e1649755297420-768x432.jpg 768w, https://openpub.buren.nl/wp-content/uploads/2022/04/bandensporen-e1649755297420.jpg 1280w\" sizes=\"(max-width: 1024px) 100vw, 1024px\" />",
                              "sizes": "(max-width: 1024px) 100vw, 1024px",
                              "srcset": "https://openpub.buren.nl/wp-content/uploads/2022/04/bandensporen-e1649755297420-1024x576.jpg 1024w, https://openpub.buren.nl/wp-content/uploads/2022/04/bandensporen-e1649755297420-300x169.jpg 300w, https://openpub.buren.nl/wp-content/uploads/2022/04/bandensporen-e1649755297420-768x432.jpg 768w, https://openpub.buren.nl/wp-content/uploads/2022/04/bandensporen-e1649755297420.jpg 1280w",
                              "meta": {
                                "width": 1280,
                                "height": 720,
                                "file": "2022/04/bandensporen-e1649755297420.jpg",
                                "sizes": {
                                  "medium": {
                                    "file": "bandensporen-e1649755297420-300x169.jpg",
                                    "width": 300,
                                    "height": 169,
                                    "mime-type": "image/jpeg",
                                    "url": "https://openpub.buren.nl/wp-content/uploads/2022/04/bandensporen-e1649755297420-300x169.jpg",
                                    "rendered": "<img width=\"300\" height=\"169\" src=\"https://openpub.buren.nl/wp-content/uploads/2022/04/bandensporen-e1649755297420-300x169.jpg\" class=\"attachment-medium size-medium\" alt=\"\" loading=\"lazy\" srcset=\"https://openpub.buren.nl/wp-content/uploads/2022/04/bandensporen-e1649755297420-300x169.jpg 300w, https://openpub.buren.nl/wp-content/uploads/2022/04/bandensporen-e1649755297420-1024x576.jpg 1024w, https://openpub.buren.nl/wp-content/uploads/2022/04/bandensporen-e1649755297420-768x432.jpg 768w, https://openpub.buren.nl/wp-content/uploads/2022/04/bandensporen-e1649755297420.jpg 1280w\" sizes=\"(max-width: 300px) 100vw, 300px\" />"
                                  },
                                  "large": {
                                    "file": "bandensporen-e1649755297420-1024x576.jpg",
                                    "width": 1024,
                                    "height": 576,
                                    "mime-type": "image/jpeg",
                                    "url": "https://openpub.buren.nl/wp-content/uploads/2022/04/bandensporen-e1649755297420-1024x576.jpg",
                                    "rendered": "<img width=\"1024\" height=\"576\" src=\"https://openpub.buren.nl/wp-content/uploads/2022/04/bandensporen-e1649755297420-1024x576.jpg\" class=\"attachment-large size-large\" alt=\"\" loading=\"lazy\" srcset=\"https://openpub.buren.nl/wp-content/uploads/2022/04/bandensporen-e1649755297420-1024x576.jpg 1024w, https://openpub.buren.nl/wp-content/uploads/2022/04/bandensporen-e1649755297420-300x169.jpg 300w, https://openpub.buren.nl/wp-content/uploads/2022/04/bandensporen-e1649755297420-768x432.jpg 768w, https://openpub.buren.nl/wp-content/uploads/2022/04/bandensporen-e1649755297420.jpg 1280w\" sizes=\"(max-width: 1024px) 100vw, 1024px\" />"
                                  },
                                  "thumbnail": {
                                    "file": "bandensporen-e1649755297420-150x150.jpg",
                                    "width": 150,
                                    "height": 150,
                                    "mime-type": "image/jpeg",
                                    "url": "https://openpub.buren.nl/wp-content/uploads/2022/04/bandensporen-e1649755297420-150x150.jpg",
                                    "rendered": "<img width=\"150\" height=\"150\" src=\"https://openpub.buren.nl/wp-content/uploads/2022/04/bandensporen-e1649755297420-150x150.jpg\" class=\"attachment-thumbnail size-thumbnail\" alt=\"\" loading=\"lazy\" />"
                                  },
                                  "medium_large": {
                                    "file": "bandensporen-e1649755297420-768x432.jpg",
                                    "width": 768,
                                    "height": 432,
                                    "mime-type": "image/jpeg",
                                    "url": "https://openpub.buren.nl/wp-content/uploads/2022/04/bandensporen-e1649755297420-768x432.jpg",
                                    "rendered": "<img width=\"768\" height=\"432\" src=\"https://openpub.buren.nl/wp-content/uploads/2022/04/bandensporen-e1649755297420-768x432.jpg\" class=\"attachment-medium_large size-medium_large\" alt=\"\" loading=\"lazy\" srcset=\"https://openpub.buren.nl/wp-content/uploads/2022/04/bandensporen-e1649755297420-768x432.jpg 768w, https://openpub.buren.nl/wp-content/uploads/2022/04/bandensporen-e1649755297420-300x169.jpg 300w, https://openpub.buren.nl/wp-content/uploads/2022/04/bandensporen-e1649755297420-1024x576.jpg 1024w, https://openpub.buren.nl/wp-content/uploads/2022/04/bandensporen-e1649755297420.jpg 1280w\" sizes=\"(max-width: 768px) 100vw, 768px\" />"
                                  },
                                  "full": {
                                    "file": "bandensporen-e1649755297420.jpg",
                                    "width": 1280,
                                    "height": 720,
                                    "mime-type": "image/jpeg",
                                    "url": "https://openpub.buren.nl/wp-content/uploads/2022/04/bandensporen-e1649755297420.jpg",
                                    "rendered": "<img width=\"1280\" height=\"720\" src=\"https://openpub.buren.nl/wp-content/uploads/2022/04/bandensporen-e1649755297420.jpg\" class=\"attachment-full size-full\" alt=\"\" loading=\"lazy\" srcset=\"https://openpub.buren.nl/wp-content/uploads/2022/04/bandensporen-e1649755297420.jpg 1280w, https://openpub.buren.nl/wp-content/uploads/2022/04/bandensporen-e1649755297420-300x169.jpg 300w, https://openpub.buren.nl/wp-content/uploads/2022/04/bandensporen-e1649755297420-1024x576.jpg 1024w, https://openpub.buren.nl/wp-content/uploads/2022/04/bandensporen-e1649755297420-768x432.jpg 768w\" sizes=\"(max-width: 1280px) 100vw, 1280px\" />"
                                  }
                                }
                              }
                            },
                            "links": [],
                            "notes": "",
                            "synonyms": "",
                            "taxonomies": {
                              "openpub-audience": [
                                {
                                  "id": 2,
                                  "name": "Inwoners",
                                  "slug": "inwoners"
                                }
                              ],
                              "openpub-type": [
                                {
                                  "id": 22,
                                  "name": "Algemeen",
                                  "slug": "algemeen"
                                }
                              ],
                              "openpub-usage": [
                                {
                                  "id": 8,
                                  "name": "Portal",
                                  "slug": "website-gemeente"
                                }
                              ],
                              "openpub-show-on": []
                            }
                          }
                        ]
                      }
                    }
                  }
                }
              }
            }
          }
        },
        "post": {
          "summary": "",
          "operationId": "post-nieuws",
          "responses": {
            "200": {
              "description": "OK",
              "content": {
                "application/json": {
                  "schema": {
                    "description": "",
                    "type": "object",
                    "x-examples": {
                      "example-1": {
                        "Nieuws": [
                          {
                            "id": 7367,
                            "title": "Voorbelasten bouwlocatie de Teisterbant",
                            "content": "<p>In de loop van 2022 start de bouw van 55 woningen in Kerk-Avezaath. Dit gebeurt aan de noordkant van het dorp.</p>\n<p>Voordat er kan worden gebouwd, moet de grond eerst worden voorbelast. Voorbelast betekent dat de grond bouwrijp gemaakt wordt. Door het voorbelasten wordt de grond verdicht en wordt de zetting (verzakking) van de grond versneld. Hiervoor wordt op de bouwlocatie een pakket van ongeveer één meter schoon zand aangebracht. Dit zand blijft een half jaar liggen.</p>\n<p>De vrachtwagens rijden de volgende routes:</p>\n<ul>\n<li>Via de Woerd, Dorpsstraat en Achterstraat wordt het zand aangevoerd door de vrachtwagens.</li>\n<li>De vrachtwagens rijden via de Achterstraat, Dorpsstraat, Noordereind en Burensedijk weer terug.</li>\n</ul>\n<p>Bij de keuze van de routes hebben we zoveel mogelijk rekening gehouden met de verkeersveiligheid en verkeersoverlast. De aanvoer van het zand start op 13 april 2022 en duurt ongeveer drie weken.</p>\n<p>Deze werkzaamheden zijn dus niet de bouwwerkzaamheden, maar de voorbereiding daarop.<br />\nOver de bouwwerkzaamheden informeren we u later. Heeft u vragen? Neem contact op met de heer R. Melis via het telefoonnummer 06 54 38 22 36.</p>\n",
                            "excerpt": "",
                            "date": "2022-04-12 11:22:03",
                            "slug": "voorbelasten-bouwlocatie-de-teisterbant",
                            "post_status": "publish",
                            "connected": {
                              "openpub-item_to_openpub-theme": [],
                              "openpub-item_to_openpub-subtheme": [],
                              "openpub-item_to_openpub-location": [],
                              "openpub-item_to_openpub-item": []
                            },
                            "downloads": [],
                            "expired": {
                              "message": "",
                              "status": false,
                              "on": {
                                "date": "2022-05-15 00:00:00.000000",
                                "timezone_type": 3,
                                "timezone": "Europe/Amsterdam"
                              }
                            },
                            "highlighted": false,
                            "image": {
                              "title": "bandensporen",
                              "description": "",
                              "caption": "",
                              "alt": "",
                              "rendered": "<img width=\"1024\" height=\"576\" src=\"https://openpub.buren.nl/wp-content/uploads/2022/04/bandensporen-e1649755297420-1024x576.jpg\" class=\"attachment-large size-large\" alt=\"\" loading=\"lazy\" srcset=\"https://openpub.buren.nl/wp-content/uploads/2022/04/bandensporen-e1649755297420-1024x576.jpg 1024w, https://openpub.buren.nl/wp-content/uploads/2022/04/bandensporen-e1649755297420-300x169.jpg 300w, https://openpub.buren.nl/wp-content/uploads/2022/04/bandensporen-e1649755297420-768x432.jpg 768w, https://openpub.buren.nl/wp-content/uploads/2022/04/bandensporen-e1649755297420.jpg 1280w\" sizes=\"(max-width: 1024px) 100vw, 1024px\" />",
                              "sizes": "(max-width: 1024px) 100vw, 1024px",
                              "srcset": "https://openpub.buren.nl/wp-content/uploads/2022/04/bandensporen-e1649755297420-1024x576.jpg 1024w, https://openpub.buren.nl/wp-content/uploads/2022/04/bandensporen-e1649755297420-300x169.jpg 300w, https://openpub.buren.nl/wp-content/uploads/2022/04/bandensporen-e1649755297420-768x432.jpg 768w, https://openpub.buren.nl/wp-content/uploads/2022/04/bandensporen-e1649755297420.jpg 1280w",
                              "meta": {
                                "width": 1280,
                                "height": 720,
                                "file": "2022/04/bandensporen-e1649755297420.jpg",
                                "sizes": {
                                  "medium": {
                                    "file": "bandensporen-e1649755297420-300x169.jpg",
                                    "width": 300,
                                    "height": 169,
                                    "mime-type": "image/jpeg",
                                    "url": "https://openpub.buren.nl/wp-content/uploads/2022/04/bandensporen-e1649755297420-300x169.jpg",
                                    "rendered": "<img width=\"300\" height=\"169\" src=\"https://openpub.buren.nl/wp-content/uploads/2022/04/bandensporen-e1649755297420-300x169.jpg\" class=\"attachment-medium size-medium\" alt=\"\" loading=\"lazy\" srcset=\"https://openpub.buren.nl/wp-content/uploads/2022/04/bandensporen-e1649755297420-300x169.jpg 300w, https://openpub.buren.nl/wp-content/uploads/2022/04/bandensporen-e1649755297420-1024x576.jpg 1024w, https://openpub.buren.nl/wp-content/uploads/2022/04/bandensporen-e1649755297420-768x432.jpg 768w, https://openpub.buren.nl/wp-content/uploads/2022/04/bandensporen-e1649755297420.jpg 1280w\" sizes=\"(max-width: 300px) 100vw, 300px\" />"
                                  },
                                  "large": {
                                    "file": "bandensporen-e1649755297420-1024x576.jpg",
                                    "width": 1024,
                                    "height": 576,
                                    "mime-type": "image/jpeg",
                                    "url": "https://openpub.buren.nl/wp-content/uploads/2022/04/bandensporen-e1649755297420-1024x576.jpg",
                                    "rendered": "<img width=\"1024\" height=\"576\" src=\"https://openpub.buren.nl/wp-content/uploads/2022/04/bandensporen-e1649755297420-1024x576.jpg\" class=\"attachment-large size-large\" alt=\"\" loading=\"lazy\" srcset=\"https://openpub.buren.nl/wp-content/uploads/2022/04/bandensporen-e1649755297420-1024x576.jpg 1024w, https://openpub.buren.nl/wp-content/uploads/2022/04/bandensporen-e1649755297420-300x169.jpg 300w, https://openpub.buren.nl/wp-content/uploads/2022/04/bandensporen-e1649755297420-768x432.jpg 768w, https://openpub.buren.nl/wp-content/uploads/2022/04/bandensporen-e1649755297420.jpg 1280w\" sizes=\"(max-width: 1024px) 100vw, 1024px\" />"
                                  },
                                  "thumbnail": {
                                    "file": "bandensporen-e1649755297420-150x150.jpg",
                                    "width": 150,
                                    "height": 150,
                                    "mime-type": "image/jpeg",
                                    "url": "https://openpub.buren.nl/wp-content/uploads/2022/04/bandensporen-e1649755297420-150x150.jpg",
                                    "rendered": "<img width=\"150\" height=\"150\" src=\"https://openpub.buren.nl/wp-content/uploads/2022/04/bandensporen-e1649755297420-150x150.jpg\" class=\"attachment-thumbnail size-thumbnail\" alt=\"\" loading=\"lazy\" />"
                                  },
                                  "medium_large": {
                                    "file": "bandensporen-e1649755297420-768x432.jpg",
                                    "width": 768,
                                    "height": 432,
                                    "mime-type": "image/jpeg",
                                    "url": "https://openpub.buren.nl/wp-content/uploads/2022/04/bandensporen-e1649755297420-768x432.jpg",
                                    "rendered": "<img width=\"768\" height=\"432\" src=\"https://openpub.buren.nl/wp-content/uploads/2022/04/bandensporen-e1649755297420-768x432.jpg\" class=\"attachment-medium_large size-medium_large\" alt=\"\" loading=\"lazy\" srcset=\"https://openpub.buren.nl/wp-content/uploads/2022/04/bandensporen-e1649755297420-768x432.jpg 768w, https://openpub.buren.nl/wp-content/uploads/2022/04/bandensporen-e1649755297420-300x169.jpg 300w, https://openpub.buren.nl/wp-content/uploads/2022/04/bandensporen-e1649755297420-1024x576.jpg 1024w, https://openpub.buren.nl/wp-content/uploads/2022/04/bandensporen-e1649755297420.jpg 1280w\" sizes=\"(max-width: 768px) 100vw, 768px\" />"
                                  },
                                  "full": {
                                    "file": "bandensporen-e1649755297420.jpg",
                                    "width": 1280,
                                    "height": 720,
                                    "mime-type": "image/jpeg",
                                    "url": "https://openpub.buren.nl/wp-content/uploads/2022/04/bandensporen-e1649755297420.jpg",
                                    "rendered": "<img width=\"1280\" height=\"720\" src=\"https://openpub.buren.nl/wp-content/uploads/2022/04/bandensporen-e1649755297420.jpg\" class=\"attachment-full size-full\" alt=\"\" loading=\"lazy\" srcset=\"https://openpub.buren.nl/wp-content/uploads/2022/04/bandensporen-e1649755297420.jpg 1280w, https://openpub.buren.nl/wp-content/uploads/2022/04/bandensporen-e1649755297420-300x169.jpg 300w, https://openpub.buren.nl/wp-content/uploads/2022/04/bandensporen-e1649755297420-1024x576.jpg 1024w, https://openpub.buren.nl/wp-content/uploads/2022/04/bandensporen-e1649755297420-768x432.jpg 768w\" sizes=\"(max-width: 1280px) 100vw, 1280px\" />"
                                  }
                                }
                              }
                            },
                            "links": [],
                            "notes": "",
                            "synonyms": "",
                            "taxonomies": {
                              "openpub-audience": [
                                {
                                  "id": 2,
                                  "name": "Inwoners",
                                  "slug": "inwoners"
                                }
                              ],
                              "openpub-type": [
                                {
                                  "id": 22,
                                  "name": "Algemeen",
                                  "slug": "algemeen"
                                }
                              ],
                              "openpub-usage": [
                                {
                                  "id": 8,
                                  "name": "Portal",
                                  "slug": "website-gemeente"
                                }
                              ],
                              "openpub-show-on": []
                            }
                          }
                        ]
                      }
                    },
                    "properties": {
                      "Nieuws": {
                        "type": "array",
                        "uniqueItems": true,
                        "minItems": 1,
                        "items": {
                          "type": "object",
                          "properties": {
                            "id": {
                              "type": "number"
                            },
                            "title": {
                              "type": "string",
                              "minLength": 1
                            },
                            "content": {
                              "type": "string",
                              "minLength": 1
                            },
                            "excerpt": {
                              "type": "string"
                            },
                            "date": {
                              "type": "string",
                              "minLength": 1
                            },
                            "slug": {
                              "type": "string",
                              "minLength": 1
                            },
                            "post_status": {
                              "type": "string",
                              "minLength": 1
                            },
                            "connected": {
                              "type": "object",
                              "properties": {
                                "openpub-item_to_openpub-theme": {
                                  "type": "array",
                                  "items": {
                                    "type": "object"
                                  }
                                },
                                "openpub-item_to_openpub-subtheme": {
                                  "type": "array",
                                  "items": {
                                    "type": "object"
                                  }
                                },
                                "openpub-item_to_openpub-location": {
                                  "type": "array",
                                  "items": {
                                    "type": "object"
                                  }
                                },
                                "openpub-item_to_openpub-item": {
                                  "type": "array",
                                  "items": {
                                    "type": "object"
                                  }
                                }
                              },
                              "required": [
                                "openpub-item_to_openpub-theme",
                                "openpub-item_to_openpub-subtheme",
                                "openpub-item_to_openpub-location",
                                "openpub-item_to_openpub-item"
                              ]
                            },
                            "downloads": {
                              "type": "array",
                              "items": {
                                "type": "object"
                              }
                            },
                            "expired": {
                              "type": "object",
                              "properties": {
                                "message": {
                                  "type": "string"
                                },
                                "status": {
                                  "type": "boolean",
                                  "default": false
                                },
                                "on": {
                                  "type": "object",
                                  "required": [
                                    "date",
                                    "timezone_type",
                                    "timezone"
                                  ],
                                  "properties": {
                                    "date": {
                                      "type": "string",
                                      "minLength": 1
                                    },
                                    "timezone_type": {
                                      "type": "number"
                                    },
                                    "timezone": {
                                      "type": "string",
                                      "minLength": 1
                                    }
                                  }
                                }
                              },
                              "required": [
                                "message",
                                "status",
                                "on"
                              ]
                            },
                            "highlighted": {
                              "type": "boolean",
                              "default": false
                            },
                            "image": {
                              "type": "object",
                              "properties": {
                                "title": {
                                  "type": "string",
                                  "minLength": 1
                                },
                                "description": {
                                  "type": "string"
                                },
                                "caption": {
                                  "type": "string"
                                },
                                "alt": {
                                  "type": "string"
                                },
                                "rendered": {
                                  "type": "string",
                                  "minLength": 1
                                },
                                "sizes": {
                                  "type": "string",
                                  "minLength": 1
                                },
                                "srcset": {
                                  "type": "string",
                                  "minLength": 1
                                },
                                "meta": {
                                  "type": "object",
                                  "required": [
                                    "width",
                                    "height",
                                    "file",
                                    "sizes"
                                  ],
                                  "properties": {
                                    "width": {
                                      "type": "number"
                                    },
                                    "height": {
                                      "type": "number"
                                    },
                                    "file": {
                                      "type": "string",
                                      "minLength": 1
                                    },
                                    "sizes": {
                                      "type": "object",
                                      "required": [
                                        "medium",
                                        "large",
                                        "thumbnail",
                                        "medium_large",
                                        "full"
                                      ],
                                      "properties": {
                                        "medium": {
                                          "type": "object",
                                          "required": [
                                            "file",
                                            "width",
                                            "height",
                                            "mime-type",
                                            "url",
                                            "rendered"
                                          ],
                                          "properties": {
                                            "file": {
                                              "type": "string",
                                              "minLength": 1
                                            },
                                            "width": {
                                              "type": "number"
                                            },
                                            "height": {
                                              "type": "number"
                                            },
                                            "mime-type": {
                                              "type": "string",
                                              "minLength": 1
                                            },
                                            "url": {
                                              "type": "string",
                                              "minLength": 1
                                            },
                                            "rendered": {
                                              "type": "string",
                                              "minLength": 1
                                            }
                                          }
                                        },
                                        "large": {
                                          "type": "object",
                                          "required": [
                                            "file",
                                            "width",
                                            "height",
                                            "mime-type",
                                            "url",
                                            "rendered"
                                          ],
                                          "properties": {
                                            "file": {
                                              "type": "string",
                                              "minLength": 1
                                            },
                                            "width": {
                                              "type": "number"
                                            },
                                            "height": {
                                              "type": "number"
                                            },
                                            "mime-type": {
                                              "type": "string",
                                              "minLength": 1
                                            },
                                            "url": {
                                              "type": "string",
                                              "minLength": 1
                                            },
                                            "rendered": {
                                              "type": "string",
                                              "minLength": 1
                                            }
                                          }
                                        },
                                        "thumbnail": {
                                          "type": "object",
                                          "required": [
                                            "file",
                                            "width",
                                            "height",
                                            "mime-type",
                                            "url",
                                            "rendered"
                                          ],
                                          "properties": {
                                            "file": {
                                              "type": "string",
                                              "minLength": 1
                                            },
                                            "width": {
                                              "type": "number"
                                            },
                                            "height": {
                                              "type": "number"
                                            },
                                            "mime-type": {
                                              "type": "string",
                                              "minLength": 1
                                            },
                                            "url": {
                                              "type": "string",
                                              "minLength": 1
                                            },
                                            "rendered": {
                                              "type": "string",
                                              "minLength": 1
                                            }
                                          }
                                        },
                                        "medium_large": {
                                          "type": "object",
                                          "required": [
                                            "file",
                                            "width",
                                            "height",
                                            "mime-type",
                                            "url",
                                            "rendered"
                                          ],
                                          "properties": {
                                            "file": {
                                              "type": "string",
                                              "minLength": 1
                                            },
                                            "width": {
                                              "type": "number"
                                            },
                                            "height": {
                                              "type": "number"
                                            },
                                            "mime-type": {
                                              "type": "string",
                                              "minLength": 1
                                            },
                                            "url": {
                                              "type": "string",
                                              "minLength": 1
                                            },
                                            "rendered": {
                                              "type": "string",
                                              "minLength": 1
                                            }
                                          }
                                        },
                                        "full": {
                                          "type": "object",
                                          "required": [
                                            "file",
                                            "width",
                                            "height",
                                            "mime-type",
                                            "url",
                                            "rendered"
                                          ],
                                          "properties": {
                                            "file": {
                                              "type": "string",
                                              "minLength": 1
                                            },
                                            "width": {
                                              "type": "number"
                                            },
                                            "height": {
                                              "type": "number"
                                            },
                                            "mime-type": {
                                              "type": "string",
                                              "minLength": 1
                                            },
                                            "url": {
                                              "type": "string",
                                              "minLength": 1
                                            },
                                            "rendered": {
                                              "type": "string",
                                              "minLength": 1
                                            }
                                          }
                                        }
                                      }
                                    }
                                  }
                                }
                              },
                              "required": [
                                "title",
                                "description",
                                "caption",
                                "alt",
                                "rendered",
                                "sizes",
                                "srcset",
                                "meta"
                              ]
                            },
                            "links": {
                              "type": "array",
                              "items": {
                                "type": "object"
                              }
                            },
                            "notes": {
                              "type": "string"
                            },
                            "synonyms": {
                              "type": "string"
                            },
                            "taxonomies": {
                              "type": "object",
                              "properties": {
                                "openpub-audience": {
                                  "type": "array",
                                  "uniqueItems": true,
                                  "minItems": 1,
                                  "items": {
                                    "type": "object",
                                    "properties": {
                                      "id": {
                                        "type": "number"
                                      },
                                      "name": {
                                        "type": "string",
                                        "minLength": 1
                                      },
                                      "slug": {
                                        "type": "string",
                                        "minLength": 1
                                      }
                                    },
                                    "required": [
                                      "id",
                                      "name",
                                      "slug"
                                    ]
                                  }
                                },
                                "openpub-type": {
                                  "type": "array",
                                  "uniqueItems": true,
                                  "minItems": 1,
                                  "items": {
                                    "type": "object",
                                    "properties": {
                                      "id": {
                                        "type": "number"
                                      },
                                      "name": {
                                        "type": "string",
                                        "minLength": 1
                                      },
                                      "slug": {
                                        "type": "string",
                                        "minLength": 1
                                      }
                                    },
                                    "required": [
                                      "id",
                                      "name",
                                      "slug"
                                    ]
                                  }
                                },
                                "openpub-usage": {
                                  "type": "array",
                                  "uniqueItems": true,
                                  "minItems": 1,
                                  "items": {
                                    "type": "object",
                                    "properties": {
                                      "id": {
                                        "type": "number"
                                      },
                                      "name": {
                                        "type": "string",
                                        "minLength": 1
                                      },
                                      "slug": {
                                        "type": "string",
                                        "minLength": 1
                                      }
                                    },
                                    "required": [
                                      "id",
                                      "name",
                                      "slug"
                                    ]
                                  }
                                },
                                "openpub-show-on": {
                                  "type": "array",
                                  "items": {
                                    "type": "object"
                                  }
                                }
                              },
                              "required": [
                                "openpub-audience",
                                "openpub-type",
                                "openpub-usage",
                                "openpub-show-on"
                              ]
                            }
                          },
                          "required": [
                            "id",
                            "title",
                            "content",
                            "excerpt",
                            "date",
                            "slug",
                            "post_status",
                            "highlighted",
                            "notes",
                            "synonyms"
                          ]
                        }
                      }
                    },
                    "required": [
                      "Nieuws"
                    ]
                  }
                }
              }
            }
          }
        }
      },
      "/nieuws/{id}": {
        "parameters": [
          {
            "schema": {
              "type": "string"
            },
            "name": "id",
            "in": "path",
            "required": true
          }
        ],
        "get": {
          "summary": "Your GET endpoint",
          "tags": [],
          "responses": {},
          "operationId": "get-nieuws-id"
        },
        "put": {
          "summary": "",
          "operationId": "put-nieuws-id",
          "responses": {
            "200": {
              "description": "OK"
            }
          }
        },
        "delete": {
          "summary": "",
          "operationId": "delete-nieuws-id",
          "responses": {
            "200": {
              "description": "OK"
            }
          }
        }
      }
    },
    "components": {
      "schemas": {
        "Nieuws": {
          "title": "Nieuws",
          "type": "object",
          "examples": [
            {
              "id": "string",
              "title": "string",
              "content": "string",
              "excerpt": "string",
              "date": "2019-08-24",
              "slug": "string",
              "post-status": "string",
              "connected": {
                "openpub-item_to_theme": [
                  null
                ],
                "openpub-item_to_openpub-subtheme": [
                  null
                ],
                "openpub-item_to_openpub-location": [
                  null
                ],
                "openpub-item_to_openpub-item": [
                  null
                ]
              },
              "downloads": [
                null
              ],
              "expired": {
                "message": "string",
                "status": true,
                "on": {
                  "date": "2019-08-24",
                  "timezone_type": 0,
                  "timezone": "string"
                }
              },
              "highlighted": true,
              "image": {
                "title": "string",
                "description": "string",
                "caption": "string",
                "alt": "string",
                "rendered": "string",
                "sizes": "string",
                "srcset": "string",
                "meta": {
                  "width": 0,
                  "height": 0,
                  "file": "string",
                  "sizes": {
                    "medium": {
                      "file": "string",
                      "width": 0,
                      "height": 0,
                      "mime-type": "string",
                      "url": "string",
                      "rendered": "string"
                    },
                    "large": {
                      "file": "string",
                      "width": 0,
                      "height": 0,
                      "mime-type": "string",
                      "url": "string",
                      "rendered": "string"
                    },
                    "thumbnail": {
                      "file": "string",
                      "width": 0,
                      "height": 0,
                      "mime-type": "string",
                      "url": "string",
                      "rendered": "string"
                    },
                    "medium_large": {
                      "file": "string",
                      "width": 0,
                      "height": 0,
                      "mime-type": "string",
                      "url": "string",
                      "rendered": "string"
                    },
                    "full": {
                      "file": "string",
                      "width": 0,
                      "height": 0,
                      "mime-type": "string",
                      "url": "string",
                      "rendered": "string"
                    }
                  }
                }
              }
            }
          ],
          "properties": {
            "id": {
              "type": "string"
            },
            "title": {
              "type": "string",
              "maxLength": 255
            },
            "content": {
              "type": "string"
            },
            "excerpt": {
              "type": "string"
            },
            "date": {
              "type": "string",
              "format": "date"
            },
            "slug": {
              "type": "string"
            },
            "post-status": {
              "type": "string"
            },
            "connected": {
              "type": "object",
              "properties": {
                "openpub-item_to_theme": {
                  "type": "array",
                  "items": {}
                },
                "openpub-item_to_openpub-subtheme": {
                  "type": "array",
                  "items": {}
                },
                "openpub-item_to_openpub-location": {
                  "type": "array",
                  "items": {}
                },
                "openpub-item_to_openpub-item": {
                  "type": "array",
                  "items": {}
                }
              }
            },
            "downloads": {
              "type": "array",
              "items": {}
            },
            "expired": {
              "type": "object",
              "properties": {
                "message": {
                  "type": "string"
                },
                "status": {
                  "type": "boolean"
                },
                "on": {
                  "type": "object",
                  "properties": {
                    "date": {
                      "type": "string",
                      "format": "date"
                    },
                    "timezone_type": {
                      "type": "integer"
                    },
                    "timezone": {
                      "type": "string"
                    }
                  }
                }
              }
            },
            "highlighted": {
              "type": "boolean"
            },
            "image": {
              "type": "object",
              "properties": {
                "title": {
                  "type": "string"
                },
                "description": {
                  "type": "string"
                },
                "caption": {
                  "type": "string"
                },
                "alt": {
                  "type": "string"
                },
                "rendered": {
                  "type": "string"
                },
                "sizes": {
                  "type": "string"
                },
                "srcset": {
                  "type": "string"
                },
                "meta": {
                  "type": "object",
                  "properties": {
                    "width": {
                      "type": [
                        "number",
                        "integer"
                      ]
                    },
                    "height": {
                      "type": [
                        "number",
                        "integer"
                      ]
                    },
                    "file": {
                      "type": "string",
                      "maxLength": 25
                    },
                    "sizes": {
                      "type": "object",
                      "properties": {
                        "medium": {
                          "type": "object",
                          "properties": {
                            "file": {
                              "type": "string"
                            },
                            "width": {
                              "type": [
                                "number",
                                "integer"
                              ]
                            },
                            "height": {
                              "type": [
                                "number",
                                "integer"
                              ]
                            },
                            "mime-type": {
                              "type": "string"
                            },
                            "url": {
                              "type": "string"
                            },
                            "rendered": {
                              "type": "string"
                            }
                          }
                        },
                        "large": {
                          "type": "object",
                          "properties": {
                            "file": {
                              "type": "string"
                            },
                            "width": {
                              "type": [
                                "number",
                                "integer"
                              ]
                            },
                            "height": {
                              "type": [
                                "number",
                                "integer"
                              ]
                            },
                            "mime-type": {
                              "type": "string"
                            },
                            "url": {
                              "type": "string"
                            },
                            "rendered": {
                              "type": "string"
                            }
                          }
                        },
                        "thumbnail": {
                          "type": "object",
                          "properties": {
                            "file": {
                              "type": "string"
                            },
                            "width": {
                              "type": [
                                "number",
                                "integer"
                              ]
                            },
                            "height": {
                              "type": [
                                "number",
                                "integer"
                              ]
                            },
                            "mime-type": {
                              "type": "string"
                            },
                            "url": {
                              "type": "string"
                            },
                            "rendered": {
                              "type": "string"
                            }
                          }
                        },
                        "medium_large": {
                          "type": "object",
                          "properties": {
                            "file": {
                              "type": "string"
                            },
                            "width": {
                              "type": [
                                "number",
                                "integer"
                              ]
                            },
                            "height": {
                              "type": [
                                "number",
                                "integer"
                              ]
                            },
                            "mime-type": {
                              "type": "string"
                            },
                            "url": {
                              "type": "string"
                            },
                            "rendered": {
                              "type": "string"
                            }
                          }
                        },
                        "full": {
                          "type": "object",
                          "properties": {
                            "file": {
                              "type": "string"
                            },
                            "width": {
                              "type": [
                                "number",
                                "integer"
                              ]
                            },
                            "height": {
                              "type": [
                                "number",
                                "integer"
                              ]
                            },
                            "mime-type": {
                              "type": "string"
                            },
                            "url": {
                              "type": "string"
                            },
                            "rendered": {
                              "type": "string"
                            }
                          }
                        }
                      }
                    }
                  }
                }
              }
            },
            "links": {
              "type": "array",
              "items": {}
            },
            "notes": {
              "type": "string"
            },
            "synonyms": {
              "type": "string"
            },
            "taxonomies": {
              "type": "object",
              "properties": {
                "openpub-audience": {
                  "type": "array",
                  "items": {
                    "type": "object",
                    "properties": {
                      "id": {
                        "type": "string"
                      },
                      "name": {
                        "type": "string"
                      },
                      "slug": {
                        "type": "string"
                      }
                    }
                  }
                },
                "openpub-type": {
                  "type": "array",
                  "items": {
                    "type": "object",
                    "properties": {
                      "id": {
                        "type": "string"
                      },
                      "name": {
                        "type": "string"
                      },
                      "slug": {
                        "type": "string"
                      }
                    }
                  }
                },
                "openpub-usage": {
                  "type": "array",
                  "items": {
                    "type": "object",
                    "properties": {
                      "id": {
                        "type": "string"
                      },
                      "name": {
                        "type": "string"
                      },
                      "slug": {
                        "type": "string"
                      }
                    }
                  }
                },
                "openpub-show-on": {
                  "type": "array",
                  "items": {}
                }
              }
            }
          }
        }
      }
    }
  }