{
    "openapi": "3.0.0",
    "collection": "https://raw.githubusercontent.com/ConductionNL/PUB_publiccode/main/PUB_OAS.json",
    "schemas": {
      "Nieuws":[
        {
            "id": 7367,
            "title": "Voorbelasten bouwlocatie de Teisterbant",
            "content": "<p>In de loop van 2022 start de bouw van 55 woningen in Kerk-Avezaath. Dit gebeurt aan de noordkant van het dorp.</p>\n<p>Voordat er kan worden gebouwd, moet de grond eerst worden voorbelast. Voorbelast betekent dat de grond bouwrijp gemaakt wordt. Door het voorbelasten wordt de grond verdicht en wordt de zetting (verzakking) van de grond versneld. Hiervoor wordt op de bouwlocatie een pakket van ongeveer één meter schoon zand aangebracht. Dit zand blijft een half jaar liggen.</p>\n<p>De vrachtwagens rijden de volgende routes:</p>\n<ul>\n<li>Via de Woerd, Dorpsstraat en Achterstraat wordt het zand aangevoerd door de vrachtwagens.</li>\n<li>De vrachtwagens rijden via de Achterstraat, Dorpsstraat, Noordereind en Burensedijk weer terug.</li>\n</ul>\n<p>Bij de keuze van de routes hebben we zoveel mogelijk rekening gehouden met de verkeersveiligheid en verkeersoverlast. De aanvoer van het zand start op 13 april 2022 en duurt ongeveer drie weken.</p>\n<p>Deze werkzaamheden zijn dus niet de bouwwerkzaamheden, maar de voorbereiding daarop.<br />\nOver de bouwwerkzaamheden informeren we u later. Heeft u vragen? Neem contact op met de heer R. Melis via het telefoonnummer 06 54 38 22 36.</p>\n",
            "excerpt": "",
            "date": "2022-04-12 11:22:03",
            "slug": "voorbelasten-bouwlocatie-de-teisterbant",
            "post_status": "publish",
            "connected": {
                "openpub-item_to_openpub-theme": [],
                "openpub-item_to_openpub-subtheme": [],
                "openpub-item_to_openpub-location": [],
                "openpub-item_to_openpub-item": []
            },
            "downloads": [],
            "expired": {
                "message": "",
                "status": false,
                "on": {
                    "date": "2022-05-15 00:00:00.000000",
                    "timezone_type": 3,
                    "timezone": "Europe/Amsterdam"
                }
            },
            "highlighted": false,
            "image": {
                "title": "bandensporen",
                "description": "",
                "caption": "",
                "alt": "",
                "rendered": "<img width=\"1024\" height=\"576\" src=\"https://openpub.buren.nl/wp-content/uploads/2022/04/bandensporen-e1649755297420-1024x576.jpg\" class=\"attachment-large size-large\" alt=\"\" loading=\"lazy\" srcset=\"https://openpub.buren.nl/wp-content/uploads/2022/04/bandensporen-e1649755297420-1024x576.jpg 1024w, https://openpub.buren.nl/wp-content/uploads/2022/04/bandensporen-e1649755297420-300x169.jpg 300w, https://openpub.buren.nl/wp-content/uploads/2022/04/bandensporen-e1649755297420-768x432.jpg 768w, https://openpub.buren.nl/wp-content/uploads/2022/04/bandensporen-e1649755297420.jpg 1280w\" sizes=\"(max-width: 1024px) 100vw, 1024px\" />",
                "sizes": "(max-width: 1024px) 100vw, 1024px",
                "srcset": "https://openpub.buren.nl/wp-content/uploads/2022/04/bandensporen-e1649755297420-1024x576.jpg 1024w, https://openpub.buren.nl/wp-content/uploads/2022/04/bandensporen-e1649755297420-300x169.jpg 300w, https://openpub.buren.nl/wp-content/uploads/2022/04/bandensporen-e1649755297420-768x432.jpg 768w, https://openpub.buren.nl/wp-content/uploads/2022/04/bandensporen-e1649755297420.jpg 1280w",
                "meta": {
                    "width": 1280,
                    "height": 720,
                    "file": "2022/04/bandensporen-e1649755297420.jpg",
                    "sizes": {
                        "medium": {
                            "file": "bandensporen-e1649755297420-300x169.jpg",
                            "width": 300,
                            "height": 169,
                            "mime-type": "image/jpeg",
                            "url": "https://openpub.buren.nl/wp-content/uploads/2022/04/bandensporen-e1649755297420-300x169.jpg",
                            "rendered": "<img width=\"300\" height=\"169\" src=\"https://openpub.buren.nl/wp-content/uploads/2022/04/bandensporen-e1649755297420-300x169.jpg\" class=\"attachment-medium size-medium\" alt=\"\" loading=\"lazy\" srcset=\"https://openpub.buren.nl/wp-content/uploads/2022/04/bandensporen-e1649755297420-300x169.jpg 300w, https://openpub.buren.nl/wp-content/uploads/2022/04/bandensporen-e1649755297420-1024x576.jpg 1024w, https://openpub.buren.nl/wp-content/uploads/2022/04/bandensporen-e1649755297420-768x432.jpg 768w, https://openpub.buren.nl/wp-content/uploads/2022/04/bandensporen-e1649755297420.jpg 1280w\" sizes=\"(max-width: 300px) 100vw, 300px\" />"
                        },
                        "large": {
                            "file": "bandensporen-e1649755297420-1024x576.jpg",
                            "width": 1024,
                            "height": 576,
                            "mime-type": "image/jpeg",
                            "url": "https://openpub.buren.nl/wp-content/uploads/2022/04/bandensporen-e1649755297420-1024x576.jpg",
                            "rendered": "<img width=\"1024\" height=\"576\" src=\"https://openpub.buren.nl/wp-content/uploads/2022/04/bandensporen-e1649755297420-1024x576.jpg\" class=\"attachment-large size-large\" alt=\"\" loading=\"lazy\" srcset=\"https://openpub.buren.nl/wp-content/uploads/2022/04/bandensporen-e1649755297420-1024x576.jpg 1024w, https://openpub.buren.nl/wp-content/uploads/2022/04/bandensporen-e1649755297420-300x169.jpg 300w, https://openpub.buren.nl/wp-content/uploads/2022/04/bandensporen-e1649755297420-768x432.jpg 768w, https://openpub.buren.nl/wp-content/uploads/2022/04/bandensporen-e1649755297420.jpg 1280w\" sizes=\"(max-width: 1024px) 100vw, 1024px\" />"
                        },
                        "thumbnail": {
                            "file": "bandensporen-e1649755297420-150x150.jpg",
                            "width": 150,
                            "height": 150,
                            "mime-type": "image/jpeg",
                            "url": "https://openpub.buren.nl/wp-content/uploads/2022/04/bandensporen-e1649755297420-150x150.jpg",
                            "rendered": "<img width=\"150\" height=\"150\" src=\"https://openpub.buren.nl/wp-content/uploads/2022/04/bandensporen-e1649755297420-150x150.jpg\" class=\"attachment-thumbnail size-thumbnail\" alt=\"\" loading=\"lazy\" />"
                        },
                        "medium_large": {
                            "file": "bandensporen-e1649755297420-768x432.jpg",
                            "width": 768,
                            "height": 432,
                            "mime-type": "image/jpeg",
                            "url": "https://openpub.buren.nl/wp-content/uploads/2022/04/bandensporen-e1649755297420-768x432.jpg",
                            "rendered": "<img width=\"768\" height=\"432\" src=\"https://openpub.buren.nl/wp-content/uploads/2022/04/bandensporen-e1649755297420-768x432.jpg\" class=\"attachment-medium_large size-medium_large\" alt=\"\" loading=\"lazy\" srcset=\"https://openpub.buren.nl/wp-content/uploads/2022/04/bandensporen-e1649755297420-768x432.jpg 768w, https://openpub.buren.nl/wp-content/uploads/2022/04/bandensporen-e1649755297420-300x169.jpg 300w, https://openpub.buren.nl/wp-content/uploads/2022/04/bandensporen-e1649755297420-1024x576.jpg 1024w, https://openpub.buren.nl/wp-content/uploads/2022/04/bandensporen-e1649755297420.jpg 1280w\" sizes=\"(max-width: 768px) 100vw, 768px\" />"
                        },
                        "full": {
                            "file": "bandensporen-e1649755297420.jpg",
                            "width": 1280,
                            "height": 720,
                            "mime-type": "image/jpeg",
                            "url": "https://openpub.buren.nl/wp-content/uploads/2022/04/bandensporen-e1649755297420.jpg",
                            "rendered": "<img width=\"1280\" height=\"720\" src=\"https://openpub.buren.nl/wp-content/uploads/2022/04/bandensporen-e1649755297420.jpg\" class=\"attachment-full size-full\" alt=\"\" loading=\"lazy\" srcset=\"https://openpub.buren.nl/wp-content/uploads/2022/04/bandensporen-e1649755297420.jpg 1280w, https://openpub.buren.nl/wp-content/uploads/2022/04/bandensporen-e1649755297420-300x169.jpg 300w, https://openpub.buren.nl/wp-content/uploads/2022/04/bandensporen-e1649755297420-1024x576.jpg 1024w, https://openpub.buren.nl/wp-content/uploads/2022/04/bandensporen-e1649755297420-768x432.jpg 768w\" sizes=\"(max-width: 1280px) 100vw, 1280px\" />"
                        }
                    }
                }
            },
            "links": [],
            "notes": "",
            "synonyms": "",
            "taxonomies": {
                "openpub-audience": [
                    {
                        "id": 2,
                        "name": "Inwoners",
                        "slug": "inwoners"
                    }
                ],
                "openpub-type": [
                    {
                        "id": 22,
                        "name": "Algemeen",
                        "slug": "algemeen"
                    }
                ],
                "openpub-usage": [
                    {
                        "id": 8,
                        "name": "Portal",
                        "slug": "website-gemeente"
                    }
                ],
                "openpub-show-on": []
            }
        }
      ]
    }
}
